README.md
setup.cfg
setup.py
hiveone_py/__init__.py
hiveone_py/hive.py
hiveone_py.egg-info/PKG-INFO
hiveone_py.egg-info/SOURCES.txt
hiveone_py.egg-info/dependency_links.txt
hiveone_py.egg-info/requires.txt
hiveone_py.egg-info/top_level.txt